{"id": 1, "title": "Modification of Assumed-Immutable Data (MAID)", "overview": "This occurs when a particular input is critical enough to the functioning of the application that it should not be modifiable at all, but it is. Certain resources are often assumed to be immutable when they are not, such as hidden form fields in web applications, cookies, and reverse DNS lookups.", "remediation": "::PHASE:Architecture and Design Operation Implementation:STRATEGY::EFFECTIVENESS::DESCRIPTION:When the data is stored or transmitted through untrusted sources that could modify the data, implement integrity checks to detect unauthorized modification, or store/transmit the data in a trusted location that is free from external influence.::", "damage": 1, "reproducability": 1, "exploitability": 1, "affected_users": 1, "discoverability": 1, "dread_total": 1, "effort": null, "type": "Imported", "poc": null, "approved": true, "risk": 1, "affected_hosts": null, "av": null, "ac": null, "au": null, "c": null, "i": null, "a": null, "e": null, "rl": null, "rc": null, "cdp": null, "td": null, "cr": null, "ir": null, "ar": null, "cvss_base": null, "cvss_impact": null, "cvss_exploitability": null, "cvss_temporal": null, "cvss_environmental": null, "cvss_modified_impact": null, "cvss_total": null, "ease": null}
